hl7apy/__init__.py
hl7apy/base_datatypes.py
hl7apy/consts.py
hl7apy/core.py
hl7apy/exceptions.py
hl7apy/factories.py
hl7apy/mllp.py
hl7apy/parser.py
hl7apy/utils.py
hl7apy/validation.py
hl7apy/v2_1/__init__.py
hl7apy/v2_1/base_datatypes.py
hl7apy/v2_1/datatypes.py
hl7apy/v2_1/fields.py
hl7apy/v2_1/groups.py
hl7apy/v2_1/messages.py
hl7apy/v2_1/segments.py
hl7apy/v2_2/__init__.py
hl7apy/v2_2/datatypes.py
hl7apy/v2_2/fields.py
hl7apy/v2_2/groups.py
hl7apy/v2_2/messages.py
hl7apy/v2_2/segments.py
hl7apy/v2_3/__init__.py
hl7apy/v2_3/datatypes.py
hl7apy/v2_3/fields.py
hl7apy/v2_3/groups.py
hl7apy/v2_3/messages.py
hl7apy/v2_3/segments.py
hl7apy/v2_3_1/__init__.py
hl7apy/v2_3_1/datatypes.py
hl7apy/v2_3_1/fields.py
hl7apy/v2_3_1/groups.py
hl7apy/v2_3_1/messages.py
hl7apy/v2_3_1/segments.py
hl7apy/v2_3_1/tables.py
hl7apy/v2_4/__init__.py
hl7apy/v2_4/datatypes.py
hl7apy/v2_4/fields.py
hl7apy/v2_4/groups.py
hl7apy/v2_4/messages.py
hl7apy/v2_4/segments.py
hl7apy/v2_4/tables.py
hl7apy/v2_5/__init__.py
hl7apy/v2_5/datatypes.py
hl7apy/v2_5/fields.py
hl7apy/v2_5/groups.py
hl7apy/v2_5/messages.py
hl7apy/v2_5/segments.py
hl7apy/v2_5/tables.py
hl7apy/v2_5_1/__init__.py
hl7apy/v2_5_1/datatypes.py
hl7apy/v2_5_1/fields.py
hl7apy/v2_5_1/groups.py
hl7apy/v2_5_1/messages.py
hl7apy/v2_5_1/segments.py
hl7apy/v2_5_1/tables.py
hl7apy/v2_6/__init__.py
hl7apy/v2_6/base_datatypes.py
hl7apy/v2_6/datatypes.py
hl7apy/v2_6/fields.py
hl7apy/v2_6/groups.py
hl7apy/v2_6/messages.py
hl7apy/v2_6/segments.py
hl7apy/v2_6/tables.py
hl7apy/v2_7/__init__.py
hl7apy/v2_7/base_datatypes.py
hl7apy/v2_7/datatypes.py
hl7apy/v2_7/fields.py
hl7apy/v2_7/groups.py
hl7apy/v2_7/messages.py
hl7apy/v2_7/segments.py
hl7apy/v2_7/tables.py
hl7apy/v2_8/__init__.py
hl7apy/v2_8/datatypes.py
hl7apy/v2_8/fields.py
hl7apy/v2_8/groups.py
hl7apy/v2_8/messages.py
hl7apy/v2_8/segments.py
hl7apy/v2_8/tables.py
hl7apy/v2_8_1/__init__.py
hl7apy/v2_8_1/datatypes.py
hl7apy/v2_8_1/fields.py
hl7apy/v2_8_1/groups.py
hl7apy/v2_8_1/messages.py
hl7apy-1.3.4.dist-info/LICENSE
hl7apy-1.3.4.dist-info/METADATA
hl7apy-1.3.4.dist-info/WHEEL
hl7apy-1.3.4.dist-info/top_level.txt
hl7apy-1.3.4.dist-info/RECORD
